{
  "deep-nourishing-cream": [
    {
      "id": 1,
      "authorName": "Urvi",
      "rating": 5,
      "title": "Gorgeous clean products that actually work",
      "body": "Good, clean non toxic products that actually work. I used the deep nourishing cream and it made a difference to my dry skin in just two weeks. It's helped myself and my daughter with eczema too. Very hydrating and soft cream - not greasy. And the smell is just devine.",
      "verified": true
    },
    {
      "id": 2,
      "authorName": "Salmana",
      "rating": 5,
      "title": "Love it!",
      "body": "It was so nice to meet you at the exhibition I bought the cream from you. It's so good, my hands feel so soft since using it and so I used it on my son's dry cheeks and it's been helping so much. Thank you for creating such a great product and I can't wait to see the affects after a month.",
      "verified": true
    },
    {
      "id": 3,
      "authorName": "Dee",
      "rating": 5,
      "title": "Absolutely love the products",
      "body": "I use all their products and it is amazing! Really gentle & nourishing on my sensitive skin. Love it!",
      "verified": true
    },
    {
      "id": 4,
      "authorName": "S.V.",
      "rating": 5,
      "title": "Always my favorite",
      "body": "",
      "verified": true
    },
    {
      "id": 5,
      "authorName": "Suman Jolly",
      "rating": 5,
      "title": "Magic in the jar",
      "body": "I'm truly amazed by this gorgeous deep nourishing cream! It has worked wonders for my son's eczema flare-ups — his skin is now much softer, calmer, and far less irritated. With regular use, I've seen a complete transformation in his skin's texture and comfort. Knowing that this cream is made entirely from natural ingredients without any harsh chemicals gives me real peace of mind. Thank you, Inherited, for creating such a beautiful and effective product.",
      "verified": true
    }
  ],
  "overnight-rejuvenation-cream": [
    {
      "id": 1,
      "authorName": "S.V.",
      "rating": 5,
      "title": "This rejuvenating night cream has become my favorite",
      "body": "",
      "verified": true
    },
    {
      "id": 2,
      "authorName": "Anthea",
      "rating": 5,
      "title": "I love this night cream!",
      "body": "Feels like luxury each evening. Divine scent, smooth and glowing skin. Noticeably improves complexion. Love this product!",
      "verified": true
    },
    {
      "id": 3,
      "authorName": "Manisha Desai",
      "rating": 5,
      "title": "An amazing discovery",
      "body": "Used deep nourishing cream previously with great results. This night cream is stellar — skin looks incredibly healthy. Absorbs quickly.",
      "verified": true
    },
    {
      "id": 4,
      "authorName": "G.R.",
      "rating": 5,
      "title": "So good!",
      "body": "Hesitant with sensitive skin, but noticed improvement within days. Skin looks excellent and feels amazing.",
      "verified": true
    },
    {
      "id": 5,
      "authorName": "Rishal Sajnani",
      "rating": 5,
      "title": "Husband 1 : Wife 0",
      "body": "Amazing product. Received unexpected compliments about skin appearance. Highly recommended for dramatic improvement.",
      "verified": true
    }
  ],
  "radiance-serum": [
    {
      "id": 1,
      "authorName": "S.V.",
      "rating": 5,
      "title": "My favorite night oil — my second purchase",
      "body": "My favorite night oil, this was my second purchase.",
      "verified": true
    },
    {
      "id": 2,
      "authorName": "Geeta K",
      "rating": 5,
      "title": "My skin looks great",
      "body": "This is the best product I have used for my skin. I am 78 and can't believe how my skin has started to look so youthful again.",
      "verified": true
    },
    {
      "id": 3,
      "authorName": "Rupi Gupta",
      "rating": 5,
      "title": "So glad I tried it",
      "body": "I started using this facial ghee serum because my daughter recommended it and I'm glad I did. It melts into the skin, feels soothing, and has brought back a lovely softness to my face.",
      "verified": true
    },
    {
      "id": 4,
      "authorName": "Priya S",
      "rating": 5,
      "title": "Love it!",
      "body": "I love, love, love this serum! Made my skin so much brighter in just a few uses!",
      "verified": true
    },
    {
      "id": 5,
      "authorName": "Puja",
      "rating": 5,
      "title": "Absolutely Amazing!",
      "body": "Why did I wait so long to buy this? I have been besotted with the deep nourishing cream for several years now and thought that was more than enough for my face. The softness is as outstanding as the cream but so much lighter on application and is non greasy. My face is visibly plumper, so darn smooth and the glow is unreal. I applied it as soon as it arrived and as I type this at 6pm, my face is still soft and has a glow. There is no shine or greasiness at all.",
      "verified": true
    }
  ],
  "ghee-oat-cleansing-balm": [
    {
      "id": 1,
      "authorName": "Jane Logan",
      "rating": 5,
      "title": "Game changer!",
      "body": "I bought this for my husband to use in the morning and he loves using it! He says it smells like being in a spa and his skin looks bright since starting it! Definitely going to be a staple!",
      "verified": true
    },
    {
      "id": 2,
      "authorName": "S.V.",
      "rating": 5,
      "title": "It's a very gentle balm",
      "body": "It's a very gentle balm.",
      "verified": true
    },
    {
      "id": 3,
      "authorName": "Natasha G",
      "rating": 5,
      "title": "Love this balm!",
      "body": "I love the Victoria Beckham eyeliner as it's waterproof but the flip side is it's a pain to remove! This cleansing balm is absolutely incredible — it removes the eyeliner effortlessly and doesn't leave my skin feeling dry like most make-up removers.",
      "verified": true
    },
    {
      "id": 4,
      "authorName": "Natasha Gupta",
      "rating": 5,
      "title": "I'm in love!",
      "body": "This weekend I just bought the brand new cleansing balm and I don't know how I coped without it! It literally melts off the make-up and I wiped it off with a soft cloth!",
      "verified": true
    }
  ],
  "ultimate-soothing-foot-cream": [
    {
      "id": 1,
      "authorName": "Sakina J",
      "rating": 5,
      "title": "Miraculous!",
      "body": "Your foot cream is a miraculous cream truly. I have underfloor heating and since moving into this property, my feet have been dry and the only thing that works for them is copious amounts of Vaseline. Even a concoction of castor oil, almond oil and rose hip oil didn't work. Your cream has made my feet supple and soft within the second use. A big thank you from me.",
      "verified": true
    },
    {
      "id": 2,
      "authorName": "Nudrat Chagtai",
      "rating": 5,
      "title": "Luxury for your feet",
      "body": "This is my favourite foot cream. I'm usually very reluctant to try new foot creams because they don't work, but this one is a winner. I'm all for using more natural products on your skin, as I'm a Nutritional Therapist and am very conscious about all the chemicals we put on our body. I love a brand that is innovative like Inherited but at the same time draws on rooted traditions.",
      "verified": true
    },
    {
      "id": 3,
      "authorName": "Aarti",
      "rating": 5,
      "title": "Great product",
      "body": "Best product I have used for foot care — highly recommend.",
      "verified": true
    },
    {
      "id": 4,
      "authorName": "Natasha Gupta",
      "rating": 5,
      "title": "Helped my battered feet!",
      "body": "I do karate bare feet so my feet get battered! I use the foot cream after every training session and my feet have never felt better!",
      "verified": true
    },
    {
      "id": 5,
      "authorName": "Bee Mistry-Kanani",
      "rating": 5,
      "title": "Amazing Foot Cream",
      "body": "I bought a gift set with 3 small creams in and my parents have continued to buy the Foot cream. It's an amazing cream and really does wonders for your feet — helps with cracked and dry skin leaving them very soft.",
      "verified": true
    }
  ],
  "nourishing-lip-care-set": [
    {
      "id": 1,
      "authorName": "Shaila P",
      "rating": 5,
      "title": "Amazing multi purpose",
      "body": "Not just nourishing on lips — I use it for multiple purposes such as dry skin patches from dermatitis, elbows and around nail bed after toe nail injury. Magical!",
      "verified": true
    },
    {
      "id": 2,
      "authorName": "Areesha Sheikh",
      "rating": 5,
      "title": "AMAZING!",
      "body": "This has transformed my skincare routine and I can't leave the house without the balm. It's honestly so moisturising and luscious — way better than Vaseline as it softens as well as locks in moisture without leaving sticky residue.",
      "verified": true
    },
    {
      "id": 3,
      "authorName": "Aanya G",
      "rating": 5,
      "title": "I wasn't sure till I tried it",
      "body": "I was skeptical using ghee on my lips because I do not like the smell of ghee. But this lip balm changed my opinion on it. I use it all the time now. 100% recommend.",
      "verified": true
    },
    {
      "id": 4,
      "authorName": "Lorna",
      "rating": 5,
      "title": "Didn't know what I needed was right here!",
      "body": "The lip scrub is not as abrasive as expected. With the balm at night, lips feel much softer in the mornings. Lipstick isn't caking anymore. Perfect size for handbag or travel.",
      "verified": true
    },
    {
      "id": 5,
      "authorName": "Paridhi S",
      "rating": 5,
      "title": "Found my holy grail lip balm",
      "body": "The texture and smell are wonderful and it keeps lips hydrated for longer. I have tried many lip balms over the years but I am in love with this one. Now never without it!",
      "verified": true
    }
  ],
  "essentials-gift-set": [
    {
      "id": 1,
      "authorName": "Mehak",
      "rating": 5,
      "title": "Love it!!",
      "body": "Absolutely amazing! The travel size is so easy to carry around, especially on summer holiday. The products are always a hit. 10/10 for sure.",
      "verified": true
    }
  ],
  "hand-and-foot-cream-bundle": [],
  "night-time-bundle": []
}
